whitebox_plugin_device_manager/pyproject.toml
whitebox_plugin_device_manager/__init__.py
whitebox_plugin_device_manager/apps.py
whitebox_plugin_device_manager/base.py
whitebox_plugin_device_manager/consts.py
whitebox_plugin_device_manager/exceptions.py
whitebox_plugin_device_manager/handlers.py
whitebox_plugin_device_manager/jsx/DeviceList.jsx
whitebox_plugin_device_manager/jsx/DeviceManagerServiceComponent.jsx
whitebox_plugin_device_manager/jsx/ToggleableDeviceList.jsx
whitebox_plugin_device_manager/jsx/Wizard.jsx
whitebox_plugin_device_manager/jsx/Wizard.test.jsx
whitebox_plugin_device_manager/jsx/WizardPageDeviceConnection.jsx
whitebox_plugin_device_manager/jsx/WizardPageDeviceConnection.test.jsx
whitebox_plugin_device_manager/jsx/WizardPageDeviceList.jsx
whitebox_plugin_device_manager/jsx/WizardPageDeviceList.test.jsx
whitebox_plugin_device_manager/jsx/WizardPageDeviceSelection.jsx
whitebox_plugin_device_manager/jsx/WizardPageDeviceSelection.test.jsx
whitebox_plugin_device_manager/jsx/__fixtures__/devices.js
whitebox_plugin_device_manager/jsx/common/CameraInputPreview.jsx
whitebox_plugin_device_manager/jsx/common/DeviceConnection.jsx
whitebox_plugin_device_manager/jsx/common/ModalFooterButtons.jsx
whitebox_plugin_device_manager/jsx/common/ModalFooterButtons.test.jsx
whitebox_plugin_device_manager/jsx/common/ModalPage.jsx
whitebox_plugin_device_manager/jsx/common/dynamic_elements/FieldElements.jsx
whitebox_plugin_device_manager/jsx/common/dynamic_elements/FieldElements.test.jsx
whitebox_plugin_device_manager/jsx/common/dynamic_elements/WizardElements.jsx
whitebox_plugin_device_manager/jsx/common/dynamic_elements/WizardElements.test.jsx
whitebox_plugin_device_manager/jsx/common/scaffolding/ModalTopNav.jsx
whitebox_plugin_device_manager/jsx/stores/device_wizard.js
whitebox_plugin_device_manager/jsx/stores/device_wizard.test.js
whitebox_plugin_device_manager/jsx/stores/devices.js
whitebox_plugin_device_manager/manager.py
whitebox_plugin_device_manager-0.1.16.dist-info/LICENSE
whitebox_plugin_device_manager-0.1.16.dist-info/METADATA
whitebox_plugin_device_manager-0.1.16.dist-info/WHEEL
whitebox_plugin_device_manager-0.1.16.dist-info/entry_points.txt
whitebox_plugin_device_manager-0.1.16.dist-info/RECORD
